examples/__init__.py
examples/kraken_ws_example.py
kraken_ws/__init__.py
kraken_ws/connect.py
kraken_ws/receive_messages.py
kraken_ws/requests.py
kraken_ws/send_messages.py
kraken_ws/config/__init__.py
kraken_ws/config/logging_config.py
kraken_ws/models/__init__.py
kraken_ws/models/kraken_instruments/__init__.py
kraken_ws/models/kraken_instruments/heartbeat_response.py
kraken_ws/models/kraken_instruments/method_response.py
kraken_ws/models/kraken_instruments/snapshot_or_update_response.py
kraken_ws/models/kraken_instruments/status_update_response.py
kraken_ws/models/kraken_instruments/subscribe_request.py
kraken_ws/models/kraken_instruments/unsubscribe_request.py
kraken_ws/models/kraken_instruments/websocket_response.py
kraken_ws/models/kraken_ticker/__init__.py
kraken_ws/models/kraken_ticker/subscribe_request.py
kraken_ws/models/kraken_ticker/ticker_response.py
kraken_ws/models/kraken_ticker/unsubscribe_request.py
kraken_ws/models/kraken_ticker/websocket_response.py
kraken_ws/utils/__init__.py
kraken_ws/utils/utils.py
kraken_websocket_sdk-0.1.4.dist-info/LICENSE
kraken_websocket_sdk-0.1.4.dist-info/METADATA
kraken_websocket_sdk-0.1.4.dist-info/WHEEL
kraken_websocket_sdk-0.1.4.dist-info/entry_points.txt
kraken_websocket_sdk-0.1.4.dist-info/top_level.txt
kraken_websocket_sdk-0.1.4.dist-info/RECORD
